[
  {
    "targetHeroId": "tigreal",
    "counterHeroId": "diggie",
    "reasons": [
      "Diggie reduces the impact of Tigreal's crowd-control engage.",
      "Time Journey helps teammates survive Tigreal's setup window."
    ],
    "counterTypes": [
      "anti-cc",
      "disengage",
      "teamfight"
    ],
    "proof": [
      {
        "id": "diggie-time-journey-vs-tigreal-engage",
        "category": "skill-interaction",
        "priority": "primary",
        "impact": "high",
        "summary": "Tigreal's main threat is an AoE crowd-control engage, while Diggie's ultimate gives nearby allies cleanse and control immunity during the engage window.",
        "worksBestWhen": [
          "Diggie saves ultimate for Tigreal's real engage.",
          "Diggie stays close enough to protect the teammates Tigreal wants to catch."
        ],
        "failureCases": [
          "Tigreal baits Diggie's ultimate before committing.",
          "Tigreal catches Diggie out of position.",
          "Tigreal engages while Diggie's ultimate is on cooldown."
        ]
      },
      {
        "id": "diggie-bush-control-vs-tigreal-setup",
        "category": "vision-awareness",
        "priority": "condition",
        "impact": "medium",
        "summary": "Diggie's bombs can help check space and reduce Tigreal's ability to start fights from hidden positions.",
        "worksBestWhen": [
          "Diggie uses bombs to scout bushes and likely engage paths before the team groups."
        ],
        "failureCases": [
          "The team walks into Tigreal's engage range without checking vision first."
        ]
      }
    ],
    "patchVersion": "starter-v1"
  },
  {
    "targetHeroId": "tigreal",
    "counterHeroId": "valir",
    "reasons": [
      "Valir can interrupt and push back frontline engage attempts.",
      "Long-range poke makes it harder for Tigreal to start clean fights."
    ],
    "counterTypes": [
      "anti-engage",
      "poke",
      "knockback"
    ],
    "proof": [
      {
        "id": "valir-vengeance-flame-vs-tigreal-cc",
        "category": "crowd-control-counter",
        "priority": "primary",
        "impact": "high",
        "summary": "Valir can cleanse himself with his ultimate, reducing Tigreal's ability to lock him down during the engage.",
        "worksBestWhen": [
          "Valir keeps his ultimate available for Tigreal's commit instead of using it early."
        ],
        "failureCases": [
          "Tigreal catches Valir after Valir's ultimate has already been used.",
          "Valir is flanked before he can react."
        ]
      },
      {
        "id": "valir-knockback-vs-tigreal-engage",
        "category": "skill-interaction",
        "priority": "primary",
        "impact": "medium",
        "summary": "Valir's knockback can push Tigreal away and interrupt short-range engage attempts before Tigreal gets an ideal setup.",
        "worksBestWhen": [
          "Valir maintains spacing and saves knockback for Tigreal's approach."
        ],
        "failureCases": [
          "Valir wastes knockback before Tigreal commits.",
          "Tigreal reaches Valir from fog or a flank angle."
        ]
      }
    ],
    "patchVersion": "starter-v1"
  },
  {
    "targetHeroId": "tigreal",
    "counterHeroId": "karrie",
    "reasons": [
      "Karrie can punish durable frontliners with sustained true damage."
    ],
    "counterTypes": [
      "tank-shred",
      "sustained-damage"
    ],
    "proof": [
      {
        "id": "karrie-true-damage-vs-tigreal-tank",
        "category": "damage-type-advantage",
        "priority": "primary",
        "impact": "medium",
        "summary": "Tigreal is a high-HP tank, while Karrie's true damage and Max HP-based damage can melt durable frontliners in extended fights.",
        "worksBestWhen": [
          "Karrie attacks safely from the backline.",
          "Karrie has enough time to apply sustained damage before being controlled."
        ],
        "failureCases": [
          "Tigreal catches Karrie before she can deal sustained damage.",
          "Karrie is poorly positioned or cannot use Purify at the right time."
        ]
      },
      {
        "id": "karrie-item-spike-vs-tigreal-frontline",
        "category": "item-power-spike",
        "priority": "secondary",
        "impact": "medium",
        "summary": "Karrie's tank-shredding pressure becomes more reliable after her core attack-speed and on-hit items are completed.",
        "worksBestWhen": [
          "Karrie reaches her core item timing before decisive teamfights."
        ],
        "failureCases": [
          "The game is decided before Karrie reaches her core item spike.",
          "Tigreal's team forces fights before Karrie has enough damage uptime."
        ]
      }
    ],
    "patchVersion": "starter-v1"
  },
  {
    "targetHeroId": "tigreal",
    "counterHeroId": "akai",
    "reasons": [
      "Akai can disrupt Tigreal's setup timing and separate Tigreal from follow-up damage."
    ],
    "counterTypes": [
      "disruption",
      "knockback",
      "anti-setter"
    ],
    "proof": [
      {
        "id": "akai-heavy-spin-vs-tigreal-setter-engage",
        "category": "teamfight-role-counter",
        "priority": "primary",
        "impact": "high",
        "summary": "Tigreal wants to catch grouped enemies as a setter tank, while Akai can disrupt formations, push Tigreal away, and separate him from team follow-up.",
        "worksBestWhen": [
          "Akai uses ultimate after Tigreal commits.",
          "Akai pushes Tigreal away from the backline.",
          "Akai has vision of Tigreal's engage path."
        ],
        "failureCases": [
          "Akai ultimate is unavailable.",
          "Tigreal catches Akai first.",
          "Akai pushes enemies in the wrong direction."
        ]
      }
    ],
    "patchVersion": "manual-proof-v1"
  },
  {
    "targetHeroId": "tigreal",
    "counterHeroId": "lunox",
    "reasons": [
      "Lunox can damage Tigreal's tanky build with magic penetration while using survival tools against engage."
    ],
    "counterTypes": [
      "magic-penetration",
      "tank-burst",
      "escape"
    ],
    "proof": [
      {
        "id": "lunox-penetration-vs-tigreal-tank-engage",
        "category": "damage-type-advantage",
        "priority": "primary",
        "impact": "medium",
        "summary": "Tigreal is a durable engage tank, while Lunox can damage tanky heroes with magic penetration and avoid some engage danger with survival tools.",
        "worksBestWhen": [
          "Lunox keeps distance before bursting.",
          "Tigreal has already used engage.",
          "Lunox has penetration or damage items."
        ],
        "failureCases": [
          "Tigreal catches Lunox before she reacts.",
          "Lunox wastes escape or invulnerability.",
          "Tigreal's team follows up immediately."
        ]
      }
    ],
    "patchVersion": "manual-proof-v1"
  }
]
